{
    "title": "gdp",
    "type": "object",
    "properties": {
        "date": {
            "type": "string",
            "default": null,
            "description": "start date of the measurement",
            "title": "date",
            "examples": "01/01/2020",
            "alias": null,
            "units": null
        },
        "time": {
            "type": "string",
            "default": null,
            "description": "start time of the measurement",
            "title": "time",
            "examples": "12:00:00",
            "alias": null,
            "units": null
        },
        "type": {
            "type": "string",
            "default": null,
            "description": "Type of GPD",
            "title": "type",
            "examples": "zen",
            "alias": null,
            "units": null
        },
        "prog_ver": {
            "type": "string",
            "default": null,
            "description": "version of hadware in the GDP",
            "title": "prog_ver",
            "examples": 0,
            "alias": null,
            "units": null
        }
    },
    "required": [],
    "description": "gdp"
}